gdsclient/__init__.py
gdsclient/call_builder.py
gdsclient/direct_endpoints.py
gdsclient/graph_data_science.py
gdsclient/indirect_endpoints.py
gdsclient/py.typed
gdsclient/algo/__init__.py
gdsclient/algo/algo_endpoints.py
gdsclient/algo/algo_proc_runner.py
gdsclient/error/__init__.py
gdsclient/error/illegal_attr_checker.py
gdsclient/error/uncallable_namespace.py
gdsclient/graph/__init__.py
gdsclient/graph/graph_endpoints.py
gdsclient/graph/graph_export_runner.py
gdsclient/graph/graph_object.py
gdsclient/graph/graph_proc_runner.py
gdsclient/graph/graph_project_runner.py
gdsclient/model/__init__.py
gdsclient/model/graphsage_model.py
gdsclient/model/model.py
gdsclient/model/model_endpoints.py
gdsclient/model/model_proc_runner.py
gdsclient/model/trained_model.py
gdsclient/pipeline/__init__.py
gdsclient/pipeline/lp_pipeline_create_runner.py
gdsclient/pipeline/lp_prediction_pipeline.py
gdsclient/pipeline/lp_training_pipeline.py
gdsclient/pipeline/nc_pipeline_create_runner.py
gdsclient/pipeline/nc_prediction_pipeline.py
gdsclient/pipeline/nc_training_pipeline.py
gdsclient/pipeline/pipeline_endpoints.py
gdsclient/pipeline/training_pipeline.py
gdsclient/query_runner/__init__.py
gdsclient/query_runner/neo4j_query_runner.py
gdsclient/query_runner/query_runner.py
gdsclient/system/__init__.py
gdsclient/system/system_endpoints.py
gdsclient/topological_lp/__init__.py
gdsclient/topological_lp/topological_lp_endpoints.py
gdsclient/topological_lp/topological_lp_runner.py
gdsclient/utils/__init__.py
gdsclient/utils/util_endpoints.py
gdsclient-0.0.6.dist-info/LICENSE
gdsclient-0.0.6.dist-info/METADATA
gdsclient-0.0.6.dist-info/WHEEL
gdsclient-0.0.6.dist-info/top_level.txt
gdsclient-0.0.6.dist-info/RECORD
