Metadata-Version: 2.1
Name: gdsclient
Version: 0.0.6
Summary: Python bindings for the Neo4j Graph Data Science library
Home-page: https://neo4j.com/product/graph-data-science/
Author: Neo4j
Author-email: team-gds@neo4j.org
License: Apache License 2.0
Project-URL: Documentation, https://neo4j.com/docs/graph-data-science/current/
Project-URL: Source, https://github.com/neo4j/gdsclient
Project-URL: Bug Tracker, https://github.com/neo4j/gdsclient/issues
Platform: UNKNOWN
Classifier: Intended Audience :: Developers
Classifier: Intended Audience :: Science/Research
Classifier: License :: OSI Approved :: Apache Software License
Classifier: Operating System :: OS Independent
Classifier: Programming Language :: Python :: 3
Classifier: Topic :: Database
Classifier: Topic :: Scientific/Engineering
Classifier: Topic :: Software Development
Classifier: Typing :: Typed
Requires-Python: >=3.6
License-File: LICENSE
Requires-Dist: neo4j
